Week9/codefest_9/dc/threshold.v
/*module threshold(
    input wire clk,
    input wire [7:0] pixel_in,
    output reg binary_out
);

initial begin
    binary_out = 0;  // Ensure known startup state
end

always @(posedge clk) begin
    // Default to 0 every cycle to prevent latch/inferred 'x'
    binary_out <= 0;

    // Simple threshold logic: pixel > 127 ⇒ white (1)
    if (pixel_in > 8'd127)
        binary_out <= 1;
end

endmodule*/

module threshold(
    input wire clk,
    input wire [7:0] pixel_in,
    input wire [7:0] threshold,
    output reg binary_out
);
initial begin
    $dumpfile("waveform.vcd");
    $dumpvars(1, clk);           // dump clock signal
    $dumpvars(1, pixel_in);      // input pixel
    $dumpvars(1, threshold);     // threshold register
    $dumpvars(1, binary_out);    // output
end

always @(posedge clk) begin
    binary_out <= (pixel_in > threshold) ? 1'b1 : 1'b0;
end




endmodule

Week9/codefest_9/waveform.vcd
$date
	Sat Jun 14 22:29:26 2025
$end
$version
	QuestaSim Version 2021.3_1
$end
$timescale
	1ps
$end

$scope module threshold $end
$var wire 1 ! clk $end
$var wire 1 " pixel_in [7] $end
$var wire 1 # pixel_in [6] $end
$var wire 1 $ pixel_in [5] $end
$var wire 1 % pixel_in [4] $end
$var wire 1 & pixel_in [3] $end
$var wire 1 ' pixel_in [2] $end
$var wire 1 ( pixel_in [1] $end
$var wire 1 ) pixel_in [0] $end
$var wire 1 * threshold [7] $end
$var wire 1 + threshold [6] $end
$var wire 1 , threshold [5] $end
$var wire 1 - threshold [4] $end
$var wire 1 . threshold [3] $end
$var wire 1 / threshold [2] $end
$var wire 1 0 threshold [1] $end
$var wire 1 1 threshold [0] $end
$var reg 1 2 binary_out $end
$upscope $end
$enddefinitions $end
#0
$dumpvars
x2
1!
z)
z(
z'
z&
z%
z$
z#
z"
01
00
0/
0.
0-
0,
0+
1*
$end
#5000
0!
#10000
1!
0)
1(
1'
0&
0%
1$
1#
0"
#15000
0!
#20000
1!
02
#25000
0!
#30000
1!
0(
1&
1%
0$
1"
#35000
0!
#40000
1!
12
#45000
0!
#50000
1!
1)
0'
0&
0%
1$
#55000
0!
#60000
1!
#65000
0!
#70000
1!
1(
1'
1&
1%
0$
0"
#75000
0!
#80000
1!
02
#85000
0!
#90000
1!
0'
0&
1$
0#
1"
#95000
0!
#100000
1!
12
#105000
0!
#110000
1!
0(
1'
1&
0"
#115000
0!
#120000
1!
02
#125000
0!
#130000
1!
0)
1(
0'
0%
1#
1"
#135000
0!
#140000
1!
12
#145000
0!
#150000
1!
1)
0$
#155000
0!
#160000
1!
#165000
0!
#170000
1!
0)
0(
1'
1%
0"
#175000
0!
#180000
1!
02
#185000
0!
#190000
1!
1)
1(
0'
0&
0%
0#
#195000
0!
#200000
1!
#205000
0!
#210000
1!
0)
1$
1#
#215000
0!
#220000
1!
#225000
0!
#230000
1!
1)
1%
1"
#235000
0!
#240000
1!
12
#245000
0!
#250000
1!
0)
1'
1&
0%
0$
0#
0"
#255000
0!
#260000
1!
02
#265000
0!
#270000
1!
1)
0(
0&
1%
1"
#275000
0!
#280000
1!
12
#285000
0!
#290000
1!
1$
1#
#295000
0!
#300000
1!
#305000
0!
#310000
1!
0)
1(
1&
0%
0#
0"
#315000
0!
#320000
1!
02
#325000
0!
#330000
1!
0'
1#
#335000
0!
#340000
1!
#345000
0!
#350000
1!
0(
1'
0&
1%
1"
#355000
0!
#360000
1!
12
#365000
0!
#370000
1!
1)
1(
0'
0%
0"
#375000
0!
#380000
1!
02
#385000
0!
#390000
1!
1&
1%
0#
1"
#395000
0!
#400000
1!
12
#405000
0!
#410000
1!
1'
0&
0%
0$
1#
0"
#415000
0!
#420000
1!
02
#425000
0!
#430000
1!
0)
0(
1%
1"
#435000
0!
#440000
1!
12
#445000
0!
#450000
1!
1)
0'
1&
0#
#455000
0!
#460000
1!
#465000
0!
#470000
1!
1(
1'
0&
0%
1#
#475000
0!
#480000
1!
#485000
0!
#490000
1!
0)
0(
1&
1%
1$
0#
#495000
0!
#500000
1!
#505000
0!
#510000
1!
1(
0%
#515000
0!
#520000
1!
#525000
0!
#530000
1!
1)
0(
0'
0&
0$
1#
0"
#535000
0!
#540000
1!
02
#545000
0!
#550000
1!
1&
1%
0#
1"
#555000
0!
#560000
1!
12
#565000
0!
#570000
1!
0)
1'
0&
0"
#575000
0!
#580000
1!
02
#585000
0!
#590000
1!
1&
0%
1$
#595000
0!
#600000
1!
#605000
0!
#610000
1!
1)
1(
0'
0$
1#
1"
#615000
0!
#620000
1!
12
#625000
0!
#630000
1!
0)
0(
1%
0#
#635000
0!
#640000
1!
#645000
0!
#650000
1!
1(
1'
0&
0%
1$
1#
0"
#655000
0!
#660000
1!
02
#665000
0!
#670000
1!
1%
0$
1"
#675000
0!
#680000
1!
12
#685000
0!
#690000
1!
0(
0'
1$
#695000
0!
#700000
1!
#705000
0!
#710000
1!
1)
1(
1'
0%
0#
0"
#715000
0!
#720000
1!
02
#725000
0!
#730000
1!
0(
0'
1&
1%
1#
#735000
0!
#740000
1!
#745000
0!
#750000
1!
0)
0$
0#
#755000
0!
#760000
1!
#765000
0!
#770000
1!
1(
0&
0%
1$
#775000
0!
#780000
1!
#785000
0!
#790000
1!
1%
1#
#795000
0!
#800000
1!
#805000
0!
#810000
1!
0$
1"
#815000
0!
#820000
1!
12
#825000
0!
#830000
1!
1)
0(
0%
0"
#835000
0!
#840000
1!
02
#845000
0!
#850000
1!
1(
1'
1&
1$
1"
#855000
0!
#860000
1!
12
#865000
0!
#870000
1!
0&
0#
0"
#875000
0!
#880000
1!
02
#885000
0!
#890000
1!
0)
1%
0$
1#
1"
#895000
0!
#900000
1!
12
#905000
0!
#910000
1!
0(
1$
#915000
0!
#920000
1!
#925000
0!
#930000
1!
1)
1(
0$
0#
#935000
0!
#940000
1!
#945000
0!
#950000
1!
0(
0'
1&
0"
#955000
0!
#960000
1!
02
#965000
0!
#970000
1!
0)
1(
0%
1#
#975000
0!
#980000
1!
#985000
0!
#990000
1!
1)
0(
0&
1%
0#
1"
#995000
0!
#1000000
1!
12
#1005000
0!
#1010000
1!
0)
1(
1'
1&
1#
#1015000
0!
#1020000
1!
#1025000
0!
#1030000
1!
0%
0#
0"
#1035000
0!
#1040000
1!
02
#1045000
0!
#1050000
1!
0'
1#
1"
#1055000
0!
#1060000
1!
12
#1065000
0!
#1070000
1!
1)
0(
1'
0&
1%
0"
#1075000
0!
#1080000
1!
02
#1085000
0!
#1090000
1!
0'
0#
1"
#1095000
0!
#1100000
1!
12
#1105000
0!
#1110000
1!
1'
1$
1#
0"
#1115000
0!
#1120000
1!
02
#1125000
0!
#1130000
1!
1(
0$
#1135000
0!
#1140000
1!
#1145000
0!
#1150000
1!
0)
0(
0'
1&
1$
0#
1"
#1155000
0!
#1160000
1!
12
#1165000
0!
#1170000
1!
1)
1'
#1175000
0!
#1180000
1!
#1185000
0!
#1190000
1!
0$
1#
#1195000
0!
#1200000
1!
#1205000
0!
#1210000
1!
0)
0&
1$
0"
#1215000
0!
#1220000
1!
02
#1225000
0!
#1230000
1!
1)
1&
0%
1"
#1235000
0!
#1240000
1!
12
#1245000
0!
#1250000
1!
0"
#1255000
0!
#1260000
1!
02
#1265000
0!
#1270000
1!
0&
1%
0$
#1275000
0!
#1280000
1!
#1285000
0!
#1290000
1!
1(
0'
0%
1$
#1295000
0!
#1300000
1!
#1305000
0!
#1310000
1!
0)
0(
1'
1&
0#
1"
#1315000
0!
#1320000
1!
12
#1325000
0!
#1330000
1!
1(
0'
0&
1#
#1335000
0!
#1340000
1!
#1345000
0!
#1350000
1!
1)
0(
1&
1%
0$
0#
#1355000
0!
#1360000
1!
#1365000
0!
#1370000
1!
1(
1'
0&
0%
1$
1#
0"
#1375000
0!
#1380000
1!
02
#1385000
0!
#1390000
1!
0'
1&
1"
#1395000
0!
#1400000
1!
12
#1405000
0!
#1410000
1!
0)
0&
1%
0$
0#
#1415000
0!
#1420000
1!
#1425000
0!
#1430000
1!
0(
1'
0%
1$
0"
#1435000
0!
#1440000
1!
02
#1445000
0!
#1450000
1!
1)
1(
1%
0$
1"
#1455000
0!
#1460000
1!
12
#1465000
0!
#1470000
1!
0)
1&
1$
0"
#1475000
0!
#1480000
1!
02
#1485000
0!
#1490000
1!
0(
0&
0%
0$
1#
#1495000
0!
#1500000
1!
#1505000
0!
#1510000
1!
1)
1%
1$
0#
1"
#1515000
0!
#1520000
1!
12
#1525000
0!
#1530000
1!
0)
1(
0'
0%
0$
#1535000
0!
#1540000
1!
#1545000
0!
#1550000
1!
0(
1$
#1555000
0!
#1560000
1!
#1565000
0!
#1570000
1!
#1575000
0!
#1580000
1!
#1585000
0!
#1590000
1!
1(
1'
#1595000
0!
#1600000
1!
#1605000
0!
#1610000
1!
1)
0(
1%
0$
#1615000
0!
#1620000
1!
#1625000
0!
#1630000
1!
0)
1(
0%
0"
#1635000
0!
#1640000
1!
02
#1645000
0!
#1650000
1!
1)
0(
1#
#1655000
0!
#1660000
1!
#1665000
0!
#1670000
1!
0#
#1675000
0!
#1680000
1!
#1685000
0!
#1690000
1!
0)
1%
1$
#1695000
0!
#1700000
1!
#1705000
0!
#1710000
1!
1)
1&
1#
1"
#1715000
0!
#1720000
1!
12
#1725000
0!
#1730000
1!
0)
0'
0&
0"
#1735000
0!
#1740000
1!
02
#1745000
0!
#1750000
1!
1(
1'
1&
0%
0$
0#
#1755000
0!
#1760000
1!
#1765000
0!
#1770000
1!
1)
0(
0'
0&
#1775000
0!
#1780000
1!
#1785000
0!
#1790000
1!
1(
#1795000
0!
#1800000
1!
#1805000
0!
#1810000
1!
0)
0(
1'
1&
1#
#1815000
0!
#1820000
1!
#1825000
0!
#1830000
1!
0'
1%
1$
1"
#1835000
0!
#1840000
1!
12
#1845000
0!
#1850000
1!
1)
1(
1'
0&
0$
0"
#1855000
0!
#1860000
1!
02
#1865000
0!
#1870000
1!
0(
0'
1&
0%
1$
1"
#1875000
0!
#1880000
1!
12
#1885000
0!
#1890000
1!
0)
1'
0&
1%
0$
#1895000
0!
#1900000
1!
#1905000
0!
#1910000
1!
0'
1&
1$
0#
#1915000
0!
#1920000
1!
#1925000
0!
#1930000
1!
1)
1(
0%
1#
#1935000
0!
#1940000
1!
#1945000
0!
#1950000
1!
0(
1'
0&
1%
#1955000
0!
#1960000
1!
#1965000
0!
#1970000
1!
0)
1(
0'
1&
0$
0#
0"
#1975000
0!
#1980000
1!
02
#1985000
0!
#1990000
1!
1)
0(
1'
0&
1#
1"
#1995000
0!
#2000000
1!
12
#2005000
0!
#2010000
1!
1&
0#
#2015000
0!
#2020000
1!
#2025000
0!
#2030000
1!
1$
1#
#2035000
0!
#2040000
1!
#2045000
0!
#2050000
1!
0)
0&
0%
0$
0"
#2055000
0!
#2060000
1!
02
#2065000
0!
#2070000
1!
0'
1%
1$
1"
#2075000
0!
#2080000
1!
12
#2085000
0!
#2090000
1!
1)
1'
0%
0#
0"
#2095000
0!
#2100000
1!
02
#2105000
0!
#2110000
1!
1(
0'
1&
1%
0$
1#
1"
#2115000
0!
#2120000
1!
12
#2125000
0!
#2130000
1!
0"
#2135000
0!
#2140000
1!
02
#2145000
0!
#2150000
1!
0)
1'
0&
1$
0#
#2155000
0!
#2160000
1!
#2165000
0!
#2170000
1!
1)
0(
0'
0%
0$
1"
#2175000
0!
#2180000
1!
12
#2185000
0!
#2190000
1!
1&
0"
#2195000
0!
#2200000
1!
02
#2205000
0!
#2210000
1!
1(
0&
1%
1$
#2215000
0!
#2220000
1!
#2225000
0!
#2230000
1!
0)
0(
0%
0$
#2235000
0!
#2240000
1!
#2245000
0!
#2250000
1!
1)
1(
1'
1&
1%
1$
1"
#2255000
0!
#2260000
1!
12
#2265000
0!
#2270000
1!
0)
0(
0&
0$
0"
#2275000
0!
#2280000
1!
02
#2285000
0!
#2290000
1!
1&
0%
1"
#2295000
0!
#2300000
1!
12
#2305000
0!
#2310000
1!
1(
1$
0"
#2315000
0!
#2320000
1!
02
#2325000
0!
#2330000
1!
1)
0'
1%
1"
#2335000
0!
#2340000
1!
12
#2345000
0!
#2350000
1!
0&
0$
#2355000
0!
#2360000
1!
#2365000
0!
#2370000
1!
0(
0%
0"
#2375000
0!
#2380000
1!
02
#2385000
0!
#2390000
1!
0)
1(
1'
1&
1%
1$
1#
1"
#2395000
0!
#2400000
1!
12
#2405000
0!
#2410000
1!
0(
0&
0$
0#
0"
#2415000
0!
#2420000
1!
02
#2425000
0!
#2430000
1!
1)
0'
1&
1"
#2435000
0!
#2440000
1!
12
#2445000
0!
#2450000
1!
1(
0&
1$
1#
#2455000
0!
#2460000
1!
#2465000
0!
#2470000
1!
0)
1'
1&
0%
0#
0"
#2475000
0!
#2480000
1!
02
#2485000
0!
#2490000
1!
0(
0'
0&
1"
#2495000
0!
#2500000
1!
12
#2505000
0!
#2510000
1!
1'
0$
1#
0"
#2515000
0!
#2520000
1!
02
#2525000
0!
#2530000
1!
1)
1(
0'
1%
0#
#2535000
0!
#2540000
1!
#2545000
0!
#2550000
1!
0)
1'
1&
1"
#2555000
0!
#2560000
1!
12
#2565000
0!
#2570000
1!
1)
0'
0%
1#
#2575000
0!
#2580000
1!
#2585000
0!
#2590000
1!
0(
0&
1%
#2595000
0!
#2600000
1!
#2605000
0!
#2610000
1!
0)
1(
0%
1$
#2615000
0!
#2620000
1!
#2625000
0!
#2630000
1!
1)
0(
1'
1&
0$
0"
#2635000
0!
#2640000
1!
02
#2645000
0!
#2650000
1!
0'
1%
1$
0#
#2655000
0!
#2660000
1!
#2665000
0!
#2670000
1!
1'
0%
0$
1#
#2675000
0!
#2680000
1!
#2685000
0!
#2690000
1!
0&
1%
0#
1"
#2695000
0!
#2700000
1!
12
#2705000
0!
#2710000
1!
0)
1&
#2715000
0!
#2720000
1!
#2725000
0!
#2730000
1!
1)
0&
0"
#2735000
0!
#2740000
1!
02
#2745000
0!
#2750000
1!
0)
0'
1$
1#
#2755000
0!
#2760000
1!
#2765000
0!
#2770000
1!
1(
1'
0$
#2775000
0!
#2780000
1!
#2785000
0!
#2790000
1!
0%
0#
1"
#2795000
0!
#2800000
1!
12
#2805000
0!
#2810000
1!
0(
1&
1%
1$
1#
#2815000
0!
#2820000
1!
#2825000
0!
#2830000
1!
0'
0$
0#
0"
#2835000
0!
#2840000
1!
02
#2845000
0!
#2850000
1!
1)
1(
1'
0%
1#
1"
#2855000
0!
#2860000
1!
12
#2865000
0!
#2870000
1!
0(
0'
0&
0#
0"
#2875000
0!
#2880000
1!
02
#2885000
0!
#2890000
1!
1(
1&
1$
1#
1"
#2895000
0!
#2900000
1!
12
#2905000
0!
#2910000
1!
0)
0&
1%
#2915000
0!
#2920000
1!
#2925000
0!
#2930000
1!
1)
0$
0#
#2935000
0!
#2940000
1!
#2945000
0!
#2950000
1!
0)
1'
1&
0%
1$
1#
0"
#2955000
0!
#2960000
1!
02
#2965000
0!
#2970000
1!
0(
0'
1%
0$
#2975000
0!
#2980000
1!
#2985000
0!
#2990000
1!
1)
1(
0%
1$
#2995000
0!
#3000000
1!
#3005000
0!
#3010000
1!
1'
0&
1"
#3015000
0!
#3020000
1!
12
#3025000
0!
#3030000
1!
0(
0$
0#
0"
#3035000
0!
#3040000
1!
02
#3045000
0!
#3050000
1!
0)
0'
1%
1$
#3055000
0!
#3060000
1!
#3065000
0!
#3070000
1!
1(
1'
1&
1#
1"
#3075000
0!
#3080000
1!
12
#3085000
0!
#3090000
1!
1)
0(
0%
0$
0#
#3095000
0!
#3100000
1!
#3105000
0!
#3110000
1!
0)
1(
0'
1#
0"
#3115000
0!
#3120000
1!
02
#3125000
0!
#3130000
1!
1%
1"
#3135000
0!
#3140000
1!
12
#3145000
0!
#3150000
1!
1)
0(
0&
0%
1$
0#
#3155000
0!
#3160000
1!
#3165000
0!
#3170000
1!
1(
1'
1%
0$
1#
0"
#3175000
0!
#3180000
1!
02
#3185000
0!
#3190000
1!
0)
0%
0#
1"
#3195000
0!
#3200000
1!
12
#3205000
0!
#3210000
1!
0'
1&
1%
1$
0"
#3215000
0!
#3220000
1!
02
#3225000
0!
#3230000
1!
0(
1'
0&
0%
1#
#3235000
0!
#3240000
1!
#3245000
0!
#3250000
1!
1(
0'
0#
1"
#3255000
0!
#3260000
1!
12
#3265000
0!
#3270000
1!
0(
1'
1&
1%
0$
#3275000
0!
#3280000
1!
#3285000
0!
#3290000
1!
1(
1$
1#
#3295000
0!
#3300000
1!
#3305000
0!
#3310000
1!
1)
0(
0'
0%
0$
0"
#3315000
0!
#3320000
1!
02
#3325000
0!
#3330000
1!
1'
1%
#3335000
0!
#3340000
1!
#3345000
0!
#3350000
1!
0)
1(
0&
0%
1$
#3355000
0!
#3360000
1!
#3365000
0!
#3370000
1!
1)
0(
0'
1&
0#
1"
#3375000
0!
#3380000
1!
12
#3385000
0!
#3390000
1!
0)
1(
1'
1%
0$
1#
#3395000
0!
#3400000
1!
#3405000
0!
#3410000
1!
1)
0(
0&
1$
0#
#3415000
0!
#3420000
1!
#3425000
0!
#3430000
1!
1(
0'
0%
0"
#3435000
0!
#3440000
1!
02
#3445000
0!
#3450000
1!
1'
1&
1%
1#
1"
#3455000
0!
#3460000
1!
12
#3465000
0!
#3470000
1!
0&
0%
0$
0"
#3475000
0!
#3480000
1!
02
#3485000
0!
#3490000
1!
0)
0'
1%
1$
1"
#3495000
0!
#3500000
1!
12
#3505000
0!
#3510000
1!
1)
1&
0%
0$
0#
0"
#3515000
0!
#3520000
1!
02
#3525000
0!
#3530000
1!
1%
1#
1"
#3535000
0!
#3540000
1!
12
#3545000
0!
#3550000
1!
0(
1'
1$
#3555000
0!
#3560000
1!
#3565000
0!
#3570000
1!
0'
0%
0$
#3575000
0!
#3580000
1!
#3585000
0!
#3590000
1!
0)
1(
0"
#3595000
0!
#3600000
1!
02
#3605000
0!
#3610000
1!
1)
1%
1$
0#
1"
#3615000
0!
#3620000
1!
12
#3625000
0!
#3630000
1!
0)
0%
0$
0"
#3635000
0!
#3640000
1!
02
#3645000
0!
#3650000
1!
0(
1#
#3655000
0!
#3660000
1!
#3665000
0!
#3670000
1!
1)
1%
1$
1"
#3675000
0!
#3680000
1!
12
#3685000
0!
#3690000
1!
1(
1'
0%
0$
#3695000
0!
#3700000
1!
#3705000
0!
#3710000
1!
0'
0&
1$
#3715000
0!
#3720000
1!
#3725000
0!
#3730000
1!
0(
1&
0$
#3735000
0!
#3740000
1!
#3745000
0!
#3750000
1!
1'
1%
0"
#3755000
0!
#3760000
1!
02
#3765000
0!
#3770000
1!
0)
1(
0%
0#
#3775000
0!
#3780000
1!
#3785000
0!
#3790000
1!
1)
0&
1$
1#
1"
#3795000
0!
#3800000
1!
12
#3805000
0!
#3810000
1!
0)
1%
0$
0#
#3815000
0!
#3820000
1!
#3825000
0!
#3830000
1!
1)
0'
1&
1$
0"
#3835000
0!
#3840000
1!
02
#3845000
0!
#3850000
1!
0(
1'
1"
#3855000
0!
#3860000
1!
12
#3865000
0!
#3870000
1!
0)
0'
0&
0%
0$
0"
#3875000
0!
#3880000
1!
02
#3885000
0!
#3890000
1!
1)
1#
1"
#3895000
0!
#3900000
1!
12
#3905000
0!
#3910000
1!
0)
1'
1%
1$
0"
#3915000
0!
#3920000
1!
02
#3925000
0!
#3930000
1!
1)
1&
0#
1"
#3935000
0!
#3940000
1!
12
#3945000
0!
#3950000
1!
1(
0'
1#
#3955000
0!
#3960000
1!
#3965000
0!
#3970000
1!
0(
0&
0#
0"
#3975000
0!
#3980000
1!
02
#3985000
0!
#3990000
1!
1(
1'
0$
#3995000
0!
#4000000
1!
#4005000
0!
#4010000
1!
0)
1&
0%
1$
1"
#4015000
0!
#4020000
1!
12
#4025000
0!
#4030000
1!
0'
0$
1#
0"
#4035000
0!
#4040000
1!
02
#4045000
0!
#4050000
1!
1)
0(
0&
0#
#4055000
0!
#4060000
1!
#4065000
0!
#4070000
1!
1&
1#
1"
#4075000
0!
#4080000
1!
12
#4085000
0!
#4090000
1!
1'
1%
1$
0#
#4095000
0!
#4100000
1!
#4105000
0!
#4110000
1!
1(
0'
0%
0$
#4115000
0!
#4120000
1!
#4125000
0!
#4130000
1!
0)
1'
1#
0"
#4135000
0!
#4140000
1!
02
#4145000
0!
#4150000
1!
1%
0#
1"
#4155000
0!
#4160000
1!
12
#4165000
0!
#4170000
1!
0'
0&
1$
0"
#4175000
0!
#4180000
1!
02
#4185000
0!
#4190000
1!
0$
1#
1"
#4195000
0!
#4200000
1!
12
#4205000
0!
#4210000
1!
1)
0(
1'
1&
0#
0"
#4215000
0!
#4220000
1!
02
#4225000
0!
#4230000
1!
1(
0'
0&
1$
#4235000
0!
#4240000
1!
#4245000
0!
#4250000
1!
1&
0%
1#
#4255000
0!
#4260000
1!
#4265000
0!
#4270000
1!
1'
0&
0$
0#
#4275000
0!
#4280000
1!
#4285000
0!
#4290000
1!
0(
0'
1&
1$
1#
1"
#4295000
0!
#4300000
1!
12
#4305000
0!
#4310000
1!
0&
0"
#4315000
0!
#4320000
1!
02
#4325000
0!
#4330000
1!
0)
1(
1'
1%
0#
#4335000
0!
#4340000
1!
#4345000
0!
#4350000
1!
1&
0$
1#
1"
#4355000
0!
#4360000
1!
12
#4365000
0!
#4370000
1!
0(
0&
0%
1$
0#
#4375000
0!
#4380000
1!
#4385000
0!
#4390000
1!
1)
1(
0'
0$
#4395000
0!
#4400000
1!
#4405000
0!
#4410000
1!
1%
1$
1#
#4415000
0!
#4420000
1!
#4425000
0!
#4430000
1!
0)
0(
1'
0%
0$
0#
0"
#4435000
0!
#4440000
1!
02
#4445000
0!
#4450000
1!
1)
1%
1$
1"
#4455000
0!
#4460000
1!
12
#4465000
0!
#4470000
1!
1(
0'
1&
1#
#4475000
0!
#4480000
1!
#4485000
0!
#4490000
1!
1'
0#
0"
#4495000
0!
#4500000
1!
02
#4505000
0!
#4510000
1!
0'
1#
#4515000
0!
#4520000
1!
#4525000
0!
#4530000
1!
0)
0(
0%
0#
1"
#4535000
0!
#4540000
1!
12
#4545000
0!
#4550000
1!
1)
1(
1'
0&
1%
0$
#4555000
0!
#4560000
1!
#4565000
0!
#4570000
1!
0)
0(
0'
1&
1$
1#
#4575000
0!
#4580000
1!
#4585000
0!
#4590000
1!
1)
1'
0&
0%
0$
#4595000
0!
#4600000
1!
#4605000
0!
#4610000
1!
1&
1%
1$
0"
#4615000
0!
#4620000
1!
02
#4625000
0!
#4630000
1!
1(
0&
#4635000
0!
#4640000
1!
#4645000
0!
#4650000
1!
0)
0'
0%
0$
0#
1"
#4655000
0!
#4660000
1!
12
#4665000
0!
#4670000
1!
0(
1'
1&
1$
0"
#4675000
0!
#4680000
1!
02
#4685000
0!
#4690000
1!
0&
1#
1"
#4695000
0!
#4700000
1!
12
#4705000
0!
#4710000
1!
1)
1(
0'
1&
0$
0#
0"
#4715000
0!
#4720000
1!
02
#4725000
0!
#4730000
1!
0)
0(
1'
0&
1$
1#
1"
#4735000
0!
#4740000
1!
12
#4745000
0!
#4750000
1!
1)
1&
0$
0#
0"
#4755000
0!
#4760000
1!
02
#4765000
0!
#4770000
1!
0&
1$
#4775000
0!
#4780000
1!
#4785000
0!
#4790000
1!
0)
1&
1%
0$
1#
1"
#4795000
0!
#4800000
1!
12
#4805000
0!
#4810000
1!
1(
0'
0&
1$
0#
0"
#4815000
0!
#4820000
1!
02
#4825000
0!
#4830000
1!
1)
1'
1&
0%
0$
#4835000
0!
#4840000
1!
#4845000
0!
#4850000
1!
0)
0(
0'
1"
#4855000
0!
#4860000
1!
12
#4865000
0!
#4870000
1!
1)
1(
1%
#4875000
0!
#4880000
1!
#4885000
0!
#4890000
1!
0)
1'
0&
0%
#4895000
0!
#4900000
1!
#4905000
0!
#4910000
1!
0'
1$
#4915000
0!
#4920000
1!
#4925000
0!
#4930000
1!
0(
1&
0"
#4935000
0!
#4940000
1!
02
#4945000
0!
#4950000
1!
1(
1'
1"
#4955000
0!
#4960000
1!
12
#4965000
0!
#4970000
1!
0(
0&
1%
0$
0"
#4975000
0!
#4980000
1!
02
#4985000
0!
#4990000
1!
0'
1&
1$
1#
#4995000
0!
#5000000
1!
#5005000
0!
#5010000
1!
1)
1(
1'
0&
0%
0#
1"
#5015000
0!
#5020000
1!
12
#5025000
0!
#5030000
1!
0'
1&
0"
#5035000
0!
#5040000
1!
02
#5045000
0!
#5050000
1!
0)
0(
0$
1#
#5055000
0!
#5060000
1!
#5065000
0!
#5070000
1!
1)
1(
1$
1"
#5075000
0!
#5080000
1!
12
#5085000
0!
#5090000
1!
0&
1%
0$
0"
#5095000
0!
#5100000
1!
02
#5105000
0!
#5110000
1!
1$
#5115000
0!
#5120000
1!
#5125000
0!
#5130000
1!
0)
1'
0%
0#
1"
#5135000
0!
#5140000
1!
12
#5145000
0!
#5150000
1!
0(
0'
1&
1%
0"
#5155000
0!
#5160000
1!
02
#5165000
0!
#5170000
1!
1)
1(
1'
0&
0%
1"
#5175000
0!
#5180000
1!
12
#5185000
0!
#5190000
1!
0)
0(
0'
1%
0$
0"
#5195000
0!
#5200000
1!
02
#5205000
0!
#5210000
1!
1)
#5215000
0!
#5220000
1!
#5225000
0!
#5230000
1!
1'
1#
#5235000
0!
#5240000
1!
#5245000
0!
#5250000
1!
0%
1$
#5255000
0!
#5260000
1!
#5265000
0!
#5270000
1!
1(
0'
0$
0#
#5275000
0!
#5280000
1!
#5285000
0!
#5290000
1!
1"
#5295000
0!
#5300000
1!
12
#5305000
0!
#5310000
1!
0(
1&
1$
0"
#5315000
0!
#5320000
1!
02
#5325000
0!
#5330000
1!
0)
1(
1#
1"
#5335000
0!
#5340000
1!
12
#5345000
0!
#5350000
1!
0&
1%
#5355000
0!
#5360000
1!
#5365000
0!
#5370000
1!
0(
1&
0$
0"
#5375000
0!
#5380000
1!
02
#5385000
0!
#5390000
1!
1(
0&
0%
1$
0#
#5395000
0!
#5400000
1!
#5405000
0!
#5410000
1!
0(
1'
1%
#5415000
0!
#5420000
1!
#5425000
0!
#5430000
1!
1)
0'
1#
1"
#5435000
0!
#5440000
1!
12
#5445000
0!
#5450000
1!
1(
1&
0#
0"
#5455000
0!
#5460000
1!
02
#5465000
0!
#5470000
1!
0(
0%
1"
#5475000
0!
#5480000
1!
12
#5485000
0!
#5490000
1!
1(
0&
1%
0"
#5495000
0!
#5500000
1!
02
#5505000
0!
#5510000
1!
1'
1#
1"
#5515000
0!
#5520000
1!
12
#5525000
0!
#5530000
1!
0(
1&
0%
0$
0#
0"
#5535000
0!
#5540000
1!
02
#5545000
0!
#5550000
1!
0)
0'
1$
1"
#5555000
0!
#5560000
1!
12
#5565000
0!
#5570000
1!
1)
1(
0&
1%
0"
#5575000
0!
#5580000
1!
02
#5585000
0!
#5590000
1!
0)
0(
0$
1"
#5595000
0!
#5600000
1!
12
#5605000
0!
#5610000
1!
1)
1$
1#
#5615000
0!
#5620000
1!
#5625000
0!
#5630000
1!
0)
0%
0#
0"
#5635000
0!
#5640000
1!
02
#5645000
0!
#5650000
1!
1)
1(
1%
1#
1"
#5655000
0!
#5660000
1!
12
#5665000
0!
#5670000
1!
0)
1'
1&
0%
0$
#5675000
0!
#5680000
1!
#5685000
0!
#5690000
1!
1)
0(
0'
1%
1$
#5695000
0!
#5700000
1!
#5705000
0!
#5710000
1!
1(
1'
0&
0%
0#
#5715000
0!
#5720000
1!
#5725000
0!
#5730000
1!
0)
0'
1&
#5735000
0!
#5740000
1!
#5745000
0!
#5750000
1!
0&
1#
0"
#5755000
0!
#5760000
1!
02
#5765000
0!
#5770000
1!
0(
1&
0$
0#
#5775000
0!
#5780000
1!
#5785000
0!
#5790000
1!
1)
1(
1$
#5795000
0!
#5800000
1!
#5805000
0!
#5810000
1!
1%
1#
1"
#5815000
0!
#5820000
1!
12
#5825000
0!
#5830000
1!
0(
1'
0%
0$
0"
#5835000
0!
#5840000
1!
02
#5845000
0!
#5850000
1!
0'
1%
#5855000
0!
#5860000
1!
#5865000
0!
#5870000
1!
1'
#5875000
0!
#5880000
1!
#5885000
0!
#5890000
1!
0)
1(
0&
0#
#5895000
0!
#5900000
1!
#5905000
0!
#5910000
1!
0(
0%
#5915000
0!
#5920000
1!
#5925000
0!
#5930000
1!
1%
1$
#5935000
0!
#5940000
1!
#5945000
0!
#5950000
1!
1(
0'
1&
0%
0$
#5955000
0!
#5960000
1!
#5965000
0!
#5970000
1!
1)
0(
0&
#5975000
0!
#5980000
1!
#5985000
0!
#5990000
1!
1&
1%
#5995000
0!
#6000000
1!
#6005000
0!
#6010000
1!
0&
0%
1"
#6015000
0!
#6020000
1!
12
#6025000
0!
#6030000
1!
1(
1&
1%
1#
#6035000
0!
#6040000
1!
#6045000
0!
#6050000
1!
0#
0"
#6055000
0!
#6060000
1!
02
#6065000
0!
#6070000
1!
1$
#6075000
0!
#6080000
1!
#6085000
0!
#6090000
1!
0&
0$
1#
#6095000
0!
#6100000
1!
#6105000
0!
#6110000
1!
0(
1'
0%
1$
1"
#6115000
0!
#6120000
1!
12
#6125000
0!
#6130000
1!
0'
1&
0#
0"
#6135000
0!
#6140000
1!
02
#6145000
0!
#6150000
1!
1(
1'
1"
#6155000
0!
#6160000
1!
12
#6165000
0!
#6170000
1!
0'
1%
0$
1#
0"
#6175000
0!
#6180000
1!
02
#6185000
0!
#6190000
1!
0)
0(
1"
#6195000
0!
#6200000
1!
12
#6205000
0!
#6210000
1!
1)
1(
0&
1$
0#
#6215000
0!
#6220000
1!
#6225000
0!
#6230000
1!
0(
1'
1&
0"
#6235000
0!
#6240000
1!
02
#6245000
0!
#6250000
1!
0)
1(
0%
1#
#6255000
0!
#6260000
1!
#6265000
0!
#6270000
1!
1)
0(
0&
1%
0$
1"
#6275000
0!
#6280000
1!
12
#6285000
0!
